TESS_Localize/TESS_Localize.py
TESS_Localize/__init__.py
TESS_Localize/error_model.npz
TESS_Localize-0.7.5.dist-info/LICENSE
TESS_Localize-0.7.5.dist-info/METADATA
TESS_Localize-0.7.5.dist-info/WHEEL
TESS_Localize-0.7.5.dist-info/top_level.txt
TESS_Localize-0.7.5.dist-info/RECORD
