Metadata-Version: 2.1
Name: TESS-Localize
Version: 0.7.5
Summary: Package for localizing variable stars in TESS Photometry
Home-page: https://github.com/Higgins00/TESS-Localize
Author: Michael Higgins
Author-email: michael.higgins@duke.edu
License: GNU General Public License v3.0
Platform: UNKNOWN
License-File: LICENSE
Requires-Dist: numpy (>=1.11)
Requires-Dist: pandas (>=1.0)
Requires-Dist: lightkurve (>=2.0.10)
Requires-Dist: lmfit (>=1.0)
Requires-Dist: matplotlib (>=3.4)
Requires-Dist: astropy (>=4.2.1)
Requires-Dist: TESS-PRF (>=0.1.3)
Requires-Dist: pygmmis
Requires-Dist: scipy
